odoo8_addon_account_invoice_validation_workflow-8.0.1.0.1.99.dev28-py2.7-nspkg.pth
odoo8_addon_account_invoice_validation_workflow-8.0.1.0.1.99.dev28.dist-info/METADATA
odoo8_addon_account_invoice_validation_workflow-8.0.1.0.1.99.dev28.dist-info/RECORD
odoo8_addon_account_invoice_validation_workflow-8.0.1.0.1.99.dev28.dist-info/WHEEL
odoo8_addon_account_invoice_validation_workflow-8.0.1.0.1.99.dev28.dist-info/namespace_packages.txt
odoo8_addon_account_invoice_validation_workflow-8.0.1.0.1.99.dev28.dist-info/top_level.txt
odoo_addons/account_invoice_validation_workflow/__init__.py
odoo_addons/account_invoice_validation_workflow/__openerp__.py
odoo_addons/account_invoice_validation_workflow/invoice.py
odoo_addons/account_invoice_validation_workflow/invoice_view.xml
odoo_addons/account_invoice_validation_workflow/invoice_wkf.xml
odoo_addons/account_invoice_validation_workflow/i18n/am.po
odoo_addons/account_invoice_validation_workflow/i18n/ar.po
odoo_addons/account_invoice_validation_workflow/i18n/bg.po
odoo_addons/account_invoice_validation_workflow/i18n/bs.po
odoo_addons/account_invoice_validation_workflow/i18n/ca.po
odoo_addons/account_invoice_validation_workflow/i18n/ca_ES.po
odoo_addons/account_invoice_validation_workflow/i18n/cs.po
odoo_addons/account_invoice_validation_workflow/i18n/da.po
odoo_addons/account_invoice_validation_workflow/i18n/de.po
odoo_addons/account_invoice_validation_workflow/i18n/el_GR.po
odoo_addons/account_invoice_validation_workflow/i18n/en_AU.po
odoo_addons/account_invoice_validation_workflow/i18n/en_GB.po
odoo_addons/account_invoice_validation_workflow/i18n/es.po
odoo_addons/account_invoice_validation_workflow/i18n/es_AR.po
odoo_addons/account_invoice_validation_workflow/i18n/es_CL.po
odoo_addons/account_invoice_validation_workflow/i18n/es_CO.po
odoo_addons/account_invoice_validation_workflow/i18n/es_CR.po
odoo_addons/account_invoice_validation_workflow/i18n/es_DO.po
odoo_addons/account_invoice_validation_workflow/i18n/es_EC.po
odoo_addons/account_invoice_validation_workflow/i18n/es_MX.po
odoo_addons/account_invoice_validation_workflow/i18n/es_PE.po
odoo_addons/account_invoice_validation_workflow/i18n/es_PY.po
odoo_addons/account_invoice_validation_workflow/i18n/es_VE.po
odoo_addons/account_invoice_validation_workflow/i18n/et.po
odoo_addons/account_invoice_validation_workflow/i18n/eu.po
