Metadata-Version: 2.1
Name: odoo8-addon-account-invoice-validation-workflow
Version: 8.0.1.0.1.99.dev28
Summary: Add "To Send" and "To Validate" states in Invoices
Home-page: http://camptocamp.com
Author: Camptocamp,Odoo Community Association (OCA)
Author-email: support@odoo-community.org
License: AGPL-3
Platform: UNKNOWN
Classifier: Programming Language :: Python
Classifier: Framework :: Odoo
Classifier: License :: OSI Approved :: GNU Affero General Public License v3
Requires-Python: ~=2.7
Requires-Dist: odoo (<9.0a,>=8.0a)
